{
  "required": true,
  "minVersion": "0.8",
  "package": "io.github.spigotrce.paradiseclientfabric.mixin.inject",
  "compatibilityLevel": "JAVA_21",
  "mixins": [
  ],
  "client": [
    "chat.ChatHudMixin",
    "chat.ChatInputSuggestorMixin",
    "chat.ChatScreenMixin",
    "chat.SuggestionWindowMixin",
    "gui.EntryListWidgetMixin",
    "gui.MultiplayerScreenMixin",
    "gui.InGameHudMixin",
    "minecraft.MinecraftClientMixin",
    "gui.ScreenMixin",
    "network.ClientConnectionMixin",
    "gui.TitleScreenMixin",
    "network.HandshakeC2SMixin",
    "minecraft.MainMixin",
    "network.SessionMixin",
    "network.ClientPlayNetworkHandlerMixin"
  ],
  "injectors": {
    "defaultRequire": 1
  }
}
